classist/__init__.py
classist-0.0.1.dist-info/LICENSE.md
classist-0.0.1.dist-info/METADATA
classist-0.0.1.dist-info/WHEEL
classist-0.0.1.dist-info/top_level.txt
classist-0.0.1.dist-info/RECORD
