Metadata-Version: 2.1
Name: classist
Version: 0.0.1
Summary: Pretty classist signature inheritance with decoration
Home-page: https://github.com/sirno/classist
License: MIT
License-File: LICENSE.md
Provides-Extra: dev
Requires-Dist: pytest; extra == "dev"
Requires-Dist: ruff; extra == "dev"
Requires-Dist: tox; extra == "dev"
